JupyterExport/__init__.py
JupyterExport/main.py
JupyterExport/assets/Anthracite.json
JupyterExport/assets/icon.ico
JupyterExport-0.1.7.dist-info/METADATA
JupyterExport-0.1.7.dist-info/WHEEL
JupyterExport-0.1.7.dist-info/entry_points.txt
JupyterExport-0.1.7.dist-info/top_level.txt
JupyterExport-0.1.7.dist-info/RECORD
