Metadata-Version: 2.1
Name: JupyterExport
Version: 0.1.7
Summary: Convert .ipynb files to .pdf/.html using a simple graphical interface.
Home-page: https://github.com/Alan-Analyst/JupyterExport
Author: Alan
Author-email: alananalyst00@gmail.com
Requires-Python: >=3.6
Requires-Dist: customtkinter
Requires-Dist: nbformat
Requires-Dist: nbconvert
Requires-Dist: IPython
Requires-Dist: Pygments
